amti/__init__.py
amti/amti.py
amti/py.typed
amti_islands-0.0.2.dist-info/METADATA
amti_islands-0.0.2.dist-info/WHEEL
amti_islands-0.0.2.dist-info/top_level.txt
amti_islands-0.0.2.dist-info/RECORD
