Metadata-Version: 2.1
Name: amti-islands
Version: 0.0.2
Summary: Object oriented islands in the South China Sea
Home-page: https://github.com/fionn/amti-islands
Author: Fionn Fitzmaurice
Project-URL: Source Code, https://github.com/fionn/amti-islands
Project-URL: Changelog, https://github.com/fionn/amti-islands/tags
Project-URL: Documentation, https://github.com/fionn/amti-islands/blob/master/README.md
Project-URL: Bug Tracker, https://github.com/fionn/amti-islands/issues
Project-URL: PyPI, https://pypi.org/project/amti-islands/
Project-URL: Download, https://github.com/fionn/amti-islands/archive/refs/heads/master.zip
Keywords: amti,south china sea,islands
Classifier: Programming Language :: Python :: 3
Classifier: Development Status :: 4 - Beta
Classifier: Intended Audience :: Developers
Classifier: Typing :: Typed
Requires-Python: >=3.10
Requires-Dist: requests
Requires-Dist: beautifulsoup4
Requires-Dist: lxml
Provides-Extra: dev
Requires-Dist: pylint ; extra == 'dev'
Requires-Dist: mypy ; extra == 'dev'
Requires-Dist: types-requests ; extra == 'dev'
